pacsltk/__init__.py
pacsltk/client.py
pacsltk/deployer.py
pacsltk/exp_parser.py
pacsltk/pacs_util.py
pacsltk/perfmodel.py
pacsltk-0.2.0.dist-info/METADATA
pacsltk-0.2.0.dist-info/WHEEL
pacsltk-0.2.0.dist-info/top_level.txt
pacsltk-0.2.0.dist-info/RECORD
